htsct/__init__.py
htsct/cli/__init__.py
htsct/cli/bdc.py
htsct/cli/init.py
htsct/cli/login.py
htsct/cli/logout.py
htsct/cli/main.py
htsct/cli/qsub.py
htsct/cli/qsub1.py
htsct/cli/task.py
htsct/cli/db/__init__.py
htsct/cli/db/main.py
htsct/cli/db/run.py
htsct/constants/__init__.py
htsct/core/__init__.py
htsct/core/buildRibbon.py
htsct/core/calculator.py
htsct/core/dataAnalysis.py
htsct/core/highThroughput.py
htsct/core/plot.py
htsct/db/__init__.py
htsct/db/api.py
htsct/db/main.py
htsct/db/scripts/__init__.py
htsct/db/scripts/database.py
htsct/db/scripts/crud/__init__.py
htsct/db/scripts/crud/c2db.py
htsct/db/scripts/crud/config.py
htsct/db/scripts/crud/ribbon.py
htsct/db/scripts/crud/taskLog.py
htsct/db/scripts/crud/vaspInput.py
htsct/db/scripts/depends/__init__.py
htsct/db/scripts/depends/c2db.py
htsct/db/scripts/depends/ribbon.py
htsct/db/scripts/models/__init__.py
htsct/db/scripts/models/c2db.py
htsct/db/scripts/models/config.py
htsct/db/scripts/models/ribbon.py
htsct/db/scripts/models/taskLog.py
htsct/db/scripts/models/vaspInput.py
htsct/db/scripts/routers/__init__.py
htsct/db/scripts/routers/c2db.py
htsct/db/scripts/routers/config.py
htsct/db/scripts/routers/ribbon.py
htsct/db/scripts/routers/taskLog.py
htsct/db/scripts/routers/vaspInput.py
htsct/db/scripts/schemas/__init__.py
htsct/db/scripts/schemas/c2db.py
htsct/db/scripts/schemas/config.py
htsct/db/scripts/schemas/ribbon.py
htsct/db/scripts/schemas/taskLog.py
htsct/db/scripts/schemas/vaspInput.py
htsct/gui/RibbonBuilder.py
htsct/gui/UI_BuildRibbon.py
htsct/gui/UI_BuildRibbon.ui
htsct/gui/UI_YacifEditer.py
htsct/gui/UI_YacifEditer.ui
htsct/gui/YacifEditer.py
htsct/gui/__init__.py
htsct/gui/_ase.py
htsct/io/__init__.py
htsct/io/vaspIO.py
htsct/statics/.guiConfig.toml
htsct/statics/__init__.py
htsct/statics/config.yaml
htsct/statics/vaspInputs.toml
htsct/utils/__init__.py
htsct/utils/_common.py
htsct/utils/qsub.py
htsct/utils/resources.py
htsct/utils/tools.py
htsct/utils/vaspOutAnlysis.py
htsct-0.0.129.dist-info/LICENSE
htsct-0.0.129.dist-info/METADATA
htsct-0.0.129.dist-info/WHEEL
htsct-0.0.129.dist-info/entry_points.txt
htsct-0.0.129.dist-info/top_level.txt
htsct-0.0.129.dist-info/RECORD
